{
  "name": "Fairies",
  "icon": "thalrathis:unused/allium_apple",
  "category": "thalrathis:races",
  "pages": [
    {
      "type": "patchouli:text",
      "text": "Fairies are small, winged creatures that levitate and resist magical damage. They are delicate, able to regenerate health when near water, but they cannot wear iron or silver armor. With their ability to regenerate and their resistance to magic, they make formidable allies in certain situations,"
    },
    {
      "type": "patchouli:text",
      "text": "though their inability to wear strong armor and their small size limit their combat prowess."
    }
  ]
}