{
  "name": "Огры",
  "icon": "thalrathis:unused/allium_apple",
  "category": "thalrathis:races",
  "pages": [
    {
      "type": "patchouli:text",
      "text": "Огры — это огромные, грубые существа, известные своей невероятной силой. Их здоровье и урон непревзойденны, что делает их ужасными противниками в бою. Однако их отсутствие ловкости и зависимость от грубой силы делают их медленными и уязвимыми для дальнобойных атак."
    },
    {
      "type": "patchouli:text",
      "text": "Огры — сила, с которой нужно считаться в ближнем бою, но их размер и отсутствие ловкости оставляют их уязвимыми для быстрых ударов."
    }
  ]
}
