{
  "name": "Авианы",
  "icon": "thalrathis:unused/allium_apple",
  "category": "thalrathis:races",
  "pages": [
    {
      "type": "patchouli:text",
      "text": "Авианы — это раса крылатых существ, известных своей непревзойдённой скоростью и ловкостью. Обладая способностью парить в воздухе и замедлять своё падение, они становятся отличными разведчиками и курьерами. Каждое утро они откладывают яйцо, странный обычай, который связывает их с их загадочным происхождением."
    },
    {
      "type": "patchouli:text",
      "text": "Однако им приходится сталкиваться с проблемой необходимости спать на больших высотах, что делает их отдых трудным в некоторых местах. Авианы быстры, но их слабости на земле делают их уязвимыми в бою."
    }
  ]
}
